{
  "title": "Oscillator, no waveform",
  "clock": {
    "bpm": 240,
    "time-signature": [
      4,
      4
    ]
  },
  "devices": [
    {
      "instrument": [
        "oscillator-1",
        {
          "oscillator": [
            {
              "midi-in": 0,
              "waveform": "noise",
              "frequency": 0
            }
          ]
        }
      ]
    }
  ],
  "patch-cables": [
    [
      "oscillator-1",
      "main-mixer"
    ]
  ],
  "patterns": [
    {
      "id": "silent-measure-1",
      "notes": [
        [
          0
        ]
      ]
    }
  ],
  "tracks": [
    {
      "id": "track-1",
      "midi-channel": 0,
      "patterns": [
        "silent-measure-1"
      ]
    }
  ]
}
